{
    "versions": [
        {
            "package_version": "1.4.2",
            "download_url": "https://github.com/ThePhar/APSM64TrackerPack/releases/download/1.4.2/pharware-sm64-pack_1.4.2.zip",
            "sha256": "ec7f4311eb38b18d517e51c686e10ca64826f94df59d686f9d7a2606d8a47a01",
            "changelog": [
                "Made 100 coins default to 'shuffled' again. Not sure why I changed it.",
                "Swapped order of Caps/Cannons logic in layout."
            ]
        },
        {
            "package_version": "1.4.1",
            "download_url": "https://github.com/ThePhar/APSM64TrackerPack/releases/download/1.4.1/pharware-sm64-pack_1.4.1.zip",
            "sha256": "106bb0f373ed769aab0726c4a10b242c91f552935958d198f3dbfc8fa9107f7e",
            "changelog": [
                "MIPS I should default to 15 stars instead of 12 stars.",
                "More tweaks to images and layouts.",
                "Area Rando back in one screen again."
            ]
        },
        {
            "package_version": "1.4.0",
            "download_url": "https://github.com/ThePhar/APSM64TrackerPack/releases/download/1.4.0/pharware-sm64-pack_1.4.0.zip",
            "sha256": "07a02c11736ed029cca21912ac4fead81b75aa463d9ca450e258614573ac4b79",
            "changelog": [
                "Removed logic for managing Bob-omb Buddies, they're now always visible. Temporary workaround for logic not taking them into account when they're not shuffled.",
                "Updated images for moves, blocks, buddies, and settings.",
                "Added a way to track Bowser III kill. Not tracked by AP (yet).",
                "Changed entrance scout-ability shapes to the new trapezoid shape, and requires the newer version of PopTracker.",
                "Fixed a logic bug for 2 locations in BitFS.",
                "Swapped entrances for THI-H and THI-T (again).",
                "Added scout logic for WMotR, TotWC, BitFS, and SA since TTC hands can now show up there."
            ]
        },
        {
            "package_version": "1.3.3",
            "download_url": "https://github.com/ThePhar/APSM64TrackerPack/releases/download/1.3.3/pharware-sm64-pack_1.3.3.zip",
            "sha256": "86cf2fad3fcd091327fa0ccc967a22b3930b00941094caaa1aef1d5a1c2826d5",
            "changelog": [
                "Reverse the entrances for THIt and THIh on castle map.",
                "Re-add missing rules for Bob-omb Buddy location in RR.",
                "Move 100 coins star location to TTC:Top region to inherit correct rules."
            ]
        },
        {
            "package_version": "1.3.2",
            "download_url": "https://github.com/ThePhar/APSM64TrackerPack/releases/download/1.3.2/pharware-sm64-pack_1.3.2.zip",
            "sha256": "a54d8e4ed90e602e9338c1dd62f35f3ef28027b9759374e445d48bee63856bce",
            "changelog": [
                "Re-add missing rule for WDW Bob-omb Buddy check.",
                "Fix issue with kick not being detecting from move vector slot data.",
                "Automatically set entrances to defaults if Area Rando is disabled.",
                "Add ability to change entrance when hovering over scout icon (image size still needs work).",
                "Add \"blue\" level for scout icon for stages like TTC and RR where you could see if TTC hands are present, even if you can't enter the stage",
                "Scout icons automatically hide if no Area Rando.",
                "Tweaks to some names."
            ]
        },
        {
            "package_version": "1.3.1",
            "download_url": "https://github.com/ThePhar/APSM64TrackerPack/releases/download/1.3.1/PharAPSM64_1.3.1.zip",
            "sha256": "b8be352630ecc71a59de233f9a0b0ff2e41fea53bab0a9d0166a91f0fd715ca0",
            "changelog": [
                "Accidentally cleared BitS entrance (and there's no way to set it without resetting all). Wups."
            ]
        },
        {
            "package_version": "1.3.0",
            "download_url": "https://github.com/ThePhar/APSM64TrackerPack/releases/download/1.3.0/PharAPSM64_1.3.0.zip",
            "sha256": "256d5d82151be0bbd725fdafd085bb0fc65ded56b49c016b8500ebc2944fe0c5",
            "changelog": [
                "Bug fix from 1.2.2: Fix island access not expecting LJ (was TJ wups).",
                "Overhaul of layout.",
                "Removal of Entrance Randomization toggle (wasn't needed).",
                "Settings for auto-tracking star requirements or entrances when connected to AP server.",
                "New images for moves (credit for which goes to Hartflip0218 on DeviantArt).",
                "Decrease size of locations summary so min window size can be smaller.",
                "Fix issue where entrances would reset if PopTracker was closed."
            ]
        },
        {
            "package_version": "1.2.2",
            "download_url": "https://github.com/ThePhar/APSM64TrackerPack/releases/download/1.2.2/PharAPSM64_1.2.2.zip",
            "sha256": "63642a93a38f116c31e90672be712c79bfd443956245d9950a790936c4bc6ef6",
            "changelog": []
        },
        {
            "package_version": "1.2.1",
            "download_url": "https://github.com/ThePhar/APSM64TrackerPack/releases/download/1.2.1/PharAPSM64_1.2.1.zip",
            "sha256": "0cfa30f73fc28ed6a1dd1b8fcbfbfd06653410f86507085b3141218e6d7de1f4",
            "changelog": [
                "Fix logic issue with Mario Wings to the Sky not requiring cannon."
            ]
        },
        {
            "package_version": "1.2.0",
            "download_url": "https://github.com/ThePhar/APSM64TrackerPack/releases/download/1.2.0/PharAPSM64_1.2.0.zip",
            "sha256": "8778249df2c491908c83099e7dae6a8e59c96824b061752a623ec2b3559d52fc",
            "changelog": [
                "Feature: Created a locations tracker that displays all locations in one tab. Does not currently factor in accessibility."
            ]
        },
        {
            "package_version": "1.1.1",
            "download_url": "https://github.com/ThePhar/APSM64TrackerPack/releases/download/1.1.1/PharAPSM64_1.1.1.zip",
            "sha256": "caea00a7dcceb81c98a9665956d9fb9d3e3c3c4375b079ec2b6ab5b271dcf0e2",
            "changelog": [
                "Feature: Add auto-update support.",
                "Refactor: Changed 'Wall Kick' icon to show 'WK' instead of 'WJ'.",
                "Bug Fix: 'Cool, Cool Mountain: Wall Kicks will Work' star no longer shows as always inaccessible."
            ]
        },
        {
            "package_version": "1.1.0",
            "download_url": "https://github.com/ThePhar/APSM64TrackerPack/releases/download/1.1.0/PharAPSM64_1.1.0.zip",
            "sha256": "4810f5e441e9a0566b4e239a6753b1fe8bee92e8ed289fb1deb7a423b6a2b221",
            "changelog": [
                "Feature: Unset accessible entrances show as blue, with a colored icon in the bottom right corner indicating accessibility level",
                "Feature: AP Auto-tracking now detects if 100 coin stars are enabled.",
                "Feature: Quality of life features for clearing or resetting multiple area entrances.",
                "Refactor: Changed ER buttons to be more legible.",
                "Bug Fix: Reloading pack resets ER state.",
                "Bug Fix: Key state is reset and recalculated on AP connection.",
                "Bug Fix: Fix multiple stage accessibility issues.",
                "Bug Fix: Area Randomization now longer enabled automatically on AP connection, if not enabled."
            ]
        },
        {
            "package_version": "1.0.1",
            "download_url": "https://github.com/ThePhar/APSM64TrackerPack/releases/download/1.0.1/phars_sm64tracker.zip",
            "sha256": "eac94a6b62633e36c37397d066eb1a35fbe3d83b84a6d31367411afd139e2048",
            "changelog": [
                "Feature: Initial official release."
            ]
        }
    ]
}